snowflake/ingest/__init__.py
snowflake/ingest/error.py
snowflake/ingest/errorcode.py
snowflake/ingest/simple_ingest_manager.py
snowflake/ingest/version.py
snowflake/ingest/utils/__init__.py
snowflake/ingest/utils/network.py
snowflake/ingest/utils/tokentools.py
snowflake/ingest/utils/uris.py
snowflake_ingest-1.0.12.dist-info/licenses/LICENSE
snowflake_ingest-1.0.12.dist-info/METADATA
snowflake_ingest-1.0.12.dist-info/WHEEL
snowflake_ingest-1.0.12.dist-info/top_level.txt
snowflake_ingest-1.0.12.dist-info/RECORD
