Metadata-Version: 2.4
Name: snowflake_ingest
Version: 1.0.12
Summary: Official SnowflakeDB File Ingest SDK
Home-page: https://www.snowflake.net
Author: Snowflake Computing
Author-email: support@snowflake.net
License: Apache
Keywords: snowflake ingest sdk copy loading
Classifier: Development Status :: 2 - Pre-Alpha
Classifier: Intended Audience :: Developers
Classifier: License :: OSI Approved :: Apache Software License
Classifier: Topic :: Database
License-File: LICENSE
Requires-Dist: pyjwt
Requires-Dist: snowflake-connector-python>=3.12.0
Requires-Dist: furl
Requires-Dist: cryptography
Requires-Dist: requests<=2.32.4
Dynamic: author
Dynamic: author-email
Dynamic: classifier
Dynamic: description
Dynamic: home-page
Dynamic: keywords
Dynamic: license
Dynamic: license-file
Dynamic: requires-dist
Dynamic: summary
